ChangeLog
INSTALL
MANIFEST.in
README
setup.py
pcli/__init__.py
pcli/log.py
pcli/text_table.py
pcli/user_input.py
pcli.egg-info/PKG-INFO
pcli.egg-info/SOURCES.txt
pcli.egg-info/dependency_links.txt
pcli.egg-info/pbr.json
pcli.egg-info/requires.txt
pcli.egg-info/top_level.txt