Metadata-Version: 1.1
Name: pcli
Version: 0.2.2
Summary: A Python package with a set of basic tools for writing programs with command line interface
Home-page: http://github.com/KonishchevDmitry/pcli
Author: Dmitry Konishchev
Author-email: konishchev@gmail.com
License: GPL3
Platform: unix
Platform: linux
Platform: osx
Classifier: Development Status :: 4 - Beta
Classifier: Intended Audience :: Developers
Classifier: License :: OSI Approved :: GNU General Public License v3 (GPLv3)
Classifier: Operating System :: MacOS :: MacOS X
Classifier: Operating System :: POSIX
Classifier: Operating System :: Unix
Classifier: Programming Language :: Python :: 3
Classifier: Topic :: Software Development :: Libraries :: Python Modules
